space_invaders/README.md
space_invaders/__init__.py
space_invaders/config.py
space_invaders/entity.py
space_invaders/level.py
space_invaders/main.py
space_invaders/pickup.py
space_invaders/run_game.py
space_invaders/spaceship.py
space_invaders/Fonts/AGENCYB.TTF
space_invaders/Fonts/AGENCYR.TTF
space_invaders/Fonts/Alien Invader Italic.ttf
space_invaders/Fonts/Alien Invader.ttf
space_invaders/Sounds/122255__jivatma07__level_complete.wav
space_invaders/Sounds/156895__halgrimm__a-shot.wav
space_invaders/Sounds/18380__inferno__hvrl.wav
space_invaders/Sounds/277403__landlucky__game-over-sfx-and-voice.wav
space_invaders/Sounds/340452__zagi2__dondolan2-loop.wav
space_invaders/Sounds/353775__samueloak89__next-scene.mp3
space_invaders/Sounds/427409__artembasov__ab_beep_or_blaster_shot.ogg
space_invaders/Sounds/565481__jakegwizdak__small-explosion.wav
space_invaders/Sounds/615809__flyingsaucerinvasion__sci-fi-laser-blaster-shot-3.wav
space_invaders/Sounds/648200__strangehorizon__glitch_blip.wav
space_invaders/Sounds/678384__jocabundus__item-pickup-v1.wav
space_invaders/Sprites/background.png
space_invaders/Sprites/default_enemy_gun.png
space_invaders/Sprites/default_enemy_projectile.png
space_invaders/Sprites/default_enemy_ship.png
space_invaders/Sprites/default_gun.png
space_invaders/Sprites/default_gun_pickup.png
space_invaders/Sprites/default_projectile.png
space_invaders/Sprites/default_ship.png
space_invaders/Sprites/explosion.png
space_invaders/Sprites/fire_rate_booster.png
space_invaders/Sprites/life.png
space_invaders/Sprites/medium_heal.png
space_invaders/Sprites/minigun.png
space_invaders/Sprites/minigun_pickup.png
space_invaders/Sprites/minigun_projectile.png
space_invaders/Sprites/repair.png
space_invaders/Sprites/rocket_gun.png
space_invaders/Sprites/rocket_gun_pickup.png
space_invaders/Sprites/rocket_projectile.png
space_invaders/Sprites/ship_explosion.png
space_invaders/Sprites/small_heal.png
space_invaders/TestResults/flake8.txt
space_invaders-0.3.2.dist-info/METADATA
space_invaders-0.3.2.dist-info/WHEEL
space_invaders-0.3.2.dist-info/entry_points.txt
space_invaders-0.3.2.dist-info/top_level.txt
space_invaders-0.3.2.dist-info/RECORD
