Metadata-Version: 2.1
Name: space-invaders
Version: 0.3.2
Summary: A cool spaceship shooter rouge like game inspired by Hyperspace Invaders
Author: Bódi Martin
Author-email: bodimartin22@gmail.com
Requires-Dist: pygame
Requires-Dist: shapely
